pyxtream/__init__.py
pyxtream/html/index.html
pyxtream/progress.py
pyxtream/pyxtream.py
pyxtream/rest_api.py
pyxtream/schemaValidator.py
pyxtream/version.py
pyxtream-0.7.3.dist-info/LICENSE
pyxtream-0.7.3.dist-info/METADATA
pyxtream-0.7.3.dist-info/WHEEL
pyxtream-0.7.3.dist-info/RECORD
