Metadata-Version: 2.3
Name: pyxtream
Version: 0.7.3
Summary: xtream IPTV loader
License: GPL3
Author: Claudio Olmi
Author-email: <superolmo2@gmail.com>
Requires-Python: >=3.9
Classifier: Development Status :: 4 - Beta
Classifier: Environment :: Console
Classifier: Intended Audience :: Developers
Classifier: Programming Language :: Python :: 3 :: Only
Classifier: License :: OSI Approved :: GNU General Public License v3 (GPLv3)
Classifier: Operating System :: OS Independent
Classifier: Natural Language :: English
Provides-Extra: flask
Requires-Dist: flask (>=3.1.0,<4.0.0) ; extra == "flask"
Requires-Dist: jsonschema (>=4.23.0,<5.0.0)
Requires-Dist: requests (>=2.32.3,<3.0.0)
